opentelemetry/exporter/jaeger/proto/grpc/__init__.py
opentelemetry/exporter/jaeger/proto/grpc/py.typed
opentelemetry/exporter/jaeger/proto/grpc/util.py
opentelemetry/exporter/jaeger/proto/grpc/version.py
opentelemetry/exporter/jaeger/proto/grpc/gen/__init__.py
opentelemetry/exporter/jaeger/proto/grpc/gen/collector_pb2.py
opentelemetry/exporter/jaeger/proto/grpc/gen/collector_pb2_grpc.py
opentelemetry/exporter/jaeger/proto/grpc/gen/model_pb2.py
opentelemetry/exporter/jaeger/proto/grpc/gen/gogoproto/gogo_pb2.py
opentelemetry/exporter/jaeger/proto/grpc/gen/google/api/annotations_pb2.py
opentelemetry/exporter/jaeger/proto/grpc/gen/google/api/http_pb2.py
opentelemetry/exporter/jaeger/proto/grpc/gen/protoc_gen_swagger/options/annotations_pb2.py
opentelemetry/exporter/jaeger/proto/grpc/gen/protoc_gen_swagger/options/openapiv2_pb2.py
opentelemetry/exporter/jaeger/proto/grpc/send/__init__.py
opentelemetry/exporter/jaeger/proto/grpc/translate/__init__.py
opentelemetry_exporter_jaeger_proto_grpc-1.19.0.dist-info/METADATA
opentelemetry_exporter_jaeger_proto_grpc-1.19.0.dist-info/WHEEL
opentelemetry_exporter_jaeger_proto_grpc-1.19.0.dist-info/entry_points.txt
opentelemetry_exporter_jaeger_proto_grpc-1.19.0.dist-info/licenses/LICENSE
opentelemetry_exporter_jaeger_proto_grpc-1.19.0.dist-info/RECORD
