Metadata-Version: 2.1
Name: opentelemetry-exporter-jaeger-proto-grpc
Version: 1.19.0
Summary: Jaeger Protobuf Exporter for OpenTelemetry
Project-URL: Homepage, https://github.com/open-telemetry/opentelemetry-python/tree/main/exporter/opentelemetry-exporter-jaeger-proto-grpc
Author-email: OpenTelemetry Authors <cncf-opentelemetry-contributors@lists.cncf.io>
License-Expression: Apache-2.0
License-File: LICENSE
Classifier: Development Status :: 5 - Production/Stable
Classifier: Intended Audience :: Developers
Classifier: License :: OSI Approved :: Apache Software License
Classifier: Programming Language :: Python
Classifier: Programming Language :: Python :: 3
Classifier: Programming Language :: Python :: 3.7
Classifier: Programming Language :: Python :: 3.8
Classifier: Programming Language :: Python :: 3.9
Classifier: Programming Language :: Python :: 3.10
Classifier: Programming Language :: Python :: 3.11
Classifier: Typing :: Typed
Requires-Python: >=3.7
Requires-Dist: googleapis-common-protos<1.56.3,~=1.52
Requires-Dist: grpcio<2.0.0,>=1.0.0
Requires-Dist: opentelemetry-api~=1.3
Requires-Dist: opentelemetry-sdk~=1.11
Provides-Extra: test
